arvos/__init__.py
arvos/builder.py
arvos/cli.py
arvos/helpers.py
arvos/tracer.py
arvos-3.0.12.dist-info/METADATA
arvos-3.0.12.dist-info/WHEEL
arvos-3.0.12.dist-info/entry_points.txt
arvos-3.0.12.dist-info/top_level.txt
arvos-3.0.12.dist-info/RECORD
