Metadata-Version: 2.1
Name: arvos
Version: 3.0.12
Summary: Arvos Command Line Utility
Author: Ayoub ED-DAFALI
Author-email: ayoub.eddafali@elastisys.com
License: UNKNOWN
Platform: UNKNOWN
Requires-Dist: docker
Requires-Dist: mako
Requires-Dist: wget
